PID_Py/PID.py
PID_Py/SetupTool.py
PID_Py/Simulation.py
PID_Py/__init__.py
PID_Py-1.2.2.dist-info/LICENSE
PID_Py-1.2.2.dist-info/METADATA
PID_Py-1.2.2.dist-info/WHEEL
PID_Py-1.2.2.dist-info/top_level.txt
PID_Py-1.2.2.dist-info/RECORD
