Metadata-Version: 2.1
Name: PID_Py
Version: 1.2.2
Summary: Simple (but complete) PID controller in Python
Author-email: ThunderTecke <thunder.tecke@gmail.com>
Maintainer-email: ThunderTecke <thunder.tecke@gmail.com>
License: MIT License
Project-URL: Homepage, https://github.com/ThunderTecke/PID_Py
Project-URL: Bug Tracker, https://github.com/ThunderTecke/PID_Py/issues
Project-URL: Change log, https://github.com/ThunderTecke/PID_Py/blob/main/CHANGELOG.md
Keywords: pid,controller,pid-controller,control,pid-control,python,raspberry,raspberrypi,raspberry-pi
Classifier: Development Status :: 4 - Beta
Classifier: Intended Audience :: Developers
Classifier: Intended Audience :: Education
Classifier: Intended Audience :: Science/Research
Classifier: Programming Language :: Python :: 3
Classifier: License :: OSI Approved :: MIT License
Classifier: Operating System :: OS Independent
Requires-Python: >=3.10
License-File: LICENSE
